gerritcli/__init__.py
gerritcli/__main__.py
gerritcli/utils.py
gerritcli/command/__init__.py
gerritcli/command/account_command.py
gerritcli/command/change_command.py
gerritcli/command/group_command.py
gerritcli/command/patch_command.py
gerritcli/command/project_command.py
gerritcli/command/server_command.py
gerritcli/command/version_command.py
python_gerrit_cli-1.0.6.dist-info/LICENSE
python_gerrit_cli-1.0.6.dist-info/METADATA
python_gerrit_cli-1.0.6.dist-info/WHEEL
python_gerrit_cli-1.0.6.dist-info/entry_points.txt
python_gerrit_cli-1.0.6.dist-info/top_level.txt
python_gerrit_cli-1.0.6.dist-info/RECORD
