Metadata-Version: 2.1
Name: python-gerrit-cli
Version: 1.0.6
Summary: Gerrit Command Line Interface
Author-email: Kai Peng <pkemb@outlook.com>
Maintainer-email: Kai Peng <pkemb@outlook.com>
License: The MIT License (MIT)
Project-URL: Homepage, https://github.com/pkemb/python-gerrit-cli
Project-URL: Bug Reports, https://github.com/pkemb/python-gerrit-cli/issues
Project-URL: Funding, https://github.com/pkemb/python-gerrit-cli
Project-URL: Say Thanks!, https://github.com/pkemb/python-gerrit-cli
Project-URL: Source, https://github.com/pkemb/python-gerrit-cli/
Keywords: Gerrit,cli,Python
Classifier: Development Status :: 3 - Alpha
Classifier: Environment :: Console
Classifier: Intended Audience :: Developers
Classifier: Topic :: Software Development :: User Interfaces
Classifier: License :: OSI Approved :: MIT License
Classifier: Programming Language :: Python :: 3
Requires-Python: >=3.0
License-File: LICENSE
Requires-Dist: prettytable
Requires-Dist: python-gerrit-api
Requires-Dist: Requests
